jzpypi/__init__.py
jzpypi/upload.py
jzpypi-50.37.49.dist-info/METADATA
jzpypi-50.37.49.dist-info/WHEEL
jzpypi-50.37.49.dist-info/entry_points.txt
jzpypi-50.37.49.dist-info/top_level.txt
jzpypi-50.37.49.dist-info/RECORD
